Workbook

Sheet Summary
A1: ORDER ANALYTICS — SQL QUERY RESULTS | 1,200 Orders | Jan 2023 – Jun 2025
A3: KEY BUSINESS METRICS
A4: Total Revenue | B4: =SUM('Revenue by Product'!C4:C10) -> 1264762 | C4: SQL: SUM(TotalPrice)
A5: Total Orders | B5: =SUM('Revenue by Product'!B4:B10) -> 1200 | C5: SQL: COUNT(*)
A6: Avg Order Value | B6: ='Revenue by Product'!D11 -> 1052.5457 | C6: SQL: AVG(TotalPrice)
A7: Delivered Orders | B7: ='Order Status'!B5 -> 247 | C7: SQL: WHERE status='Delivered'
A8: Delivery Rate | B8: ='Order Status'!C5/100 -> 0.00206 | C8: SQL: COUNT(*)/total
A10: REVENUE SNAPSHOT BY PRODUCT
A11: Product | B11: Orders | C11: Total Revenue ($) | D11: Avg Order ($) | E11: % of Total Revenue
A12: Chair | B12: 178 | C12: 195620.11 | D12: 1098.99 | E12: =C12/SUM(C12:C18) -> 0.15466951
A13: Printer | B13: 181 | C13: 195612.61 | D13: 1080.73 | E13: =C13/SUM(C12:C18) -> 0.15466358
A14: Laptop | B14: 173 | C14: 192126.56 | D14: 1110.56 | E14: =C14/SUM(C12:C18) -> 0.15190729
A15: Tablet | B15: 179 | C15: 186568.95 | D15: 1042.28 | E15: =C15/SUM(C12:C18) -> 0.14751309
A16: Monitor | B16: 163 | C16: 175651.41 | D16: 1077.62 | E16: =C16/SUM(C12:C18) -> 0.138881
A17: Desk | B17: 170 | C17: 167459.93 | D17: 985.06 | E17: =C17/SUM(C12:C18) -> 0.13240431
A18: Phone | B18: 156 | C18: 151722.39 | D18: 972.58 | E18: =C18/SUM(C12:C18) -> 0.11996122
A19: TOTAL | B19: =SUM(B12:B18) -> 1200 | C19: =SUM(C12:C18) -> 1264762 | D19: =AVERAGE(D12:D18) -> 1052.5457 | E19: =SUM(E12:E18) -> 1

Sheet Revenue by Product
A1: REVENUE BY PRODUCT — GROUP BY + SUM + COUNT + AVG
A2: SELECT Product, COUNT(*) AS OrderCount, ROUND(SUM(TotalPrice),2) AS TotalRevenue, ROUND(AVG(TotalPrice),2) AS AvgOrderValue FROM orders GROUP BY Product ORDER BY TotalRevenue DESC
A3: Product | B3: Order Count | C3: Total Revenue | D3: Avg Order Value | E3: % of Revenue
A4: Chair | B4: 178 | C4: 195620.11 | D4: 1098.99 | E4: =C4/SUM($C$4:$C$10) -> 0.15466951
A5: Printer | B5: 181 | C5: 195612.61 | D5: 1080.73 | E5: =C5/SUM($C$4:$C$10) -> 0.15466358
A6: Laptop | B6: 173 | C6: 192126.56 | D6: 1110.56 | E6: =C6/SUM($C$4:$C$10) -> 0.15190729
A7: Tablet | B7: 179 | C7: 186568.95 | D7: 1042.28 | E7: =C7/SUM($C$4:$C$10) -> 0.14751309
A8: Monitor | B8: 163 | C8: 175651.41 | D8: 1077.62 | E8: =C8/SUM($C$4:$C$10) -> 0.138881
A9: Desk | B9: 170 | C9: 167459.93 | D9: 985.06 | E9: =C9/SUM($C$4:$C$10) -> 0.13240431
A10: Phone | B10: 156 | C10: 151722.39 | D10: 972.58 | E10: =C10/SUM($C$4:$C$10) -> 0.11996122
A11: TOTAL | B11: =SUM(B4:B10) -> 1200 | C11: =SUM(C4:C10) -> 1264762 | D11: =AVERAGE(D4:D10) -> 1052.5457 | E11: 100.0%

Sheet Order Status
A1: ORDER STATUS BREAKDOWN — COUNT + WHERE + GROUP BY
A2: SELECT OrderStatus, COUNT(*) AS Count, ROUND(COUNT(*)*100.0/(SELECT COUNT(*) FROM orders),1) AS Pct FROM orders GROUP BY OrderStatus ORDER BY Count DESC
A3: Order Status | B3: Count | C3: Pct % | D3: SQL Filter
A4: Cancelled | B4: 250 | C4: 0.208 | D4: WHERE OrderStatus = 'Cancelled'
A5: Returned | B5: 247 | C5: 0.206 | D5: WHERE OrderStatus = 'Returned'
A6: Pending | B6: 237 | C6: 0.198 | D6: WHERE OrderStatus = 'Pending'
A7: Shipped | B7: 235 | C7: 0.196 | D7: WHERE OrderStatus = 'Shipped'
A8: Delivered | B8: 231 | C8: 0.193 | D8: WHERE OrderStatus = 'Delivered'
A9: TOTAL | B9: =SUM(B4:B8) -> 1200 | C9: =SUM(C4:C8) -> 1.001

Sheet Payment Method
A1: REVENUE BY PAYMENT METHOD — SUM + COUNT + GROUP BY
A2: SELECT PaymentMethod, COUNT(*) AS Count, ROUND(SUM(TotalPrice),2) AS Revenue FROM orders GROUP BY PaymentMethod ORDER BY Revenue DESC
A3: Payment Method | B3: Order Count | C3: Revenue | D3: Avg per Order
A4: Credit Card | B4: 234 | C4: 263847.63 | D4: =C4/B4 -> 1127.554
A5: Online | B5: 258 | C5: 262442.94 | D5: =C5/B5 -> 1017.2207
A6: Cash | B6: 246 | C6: 259786.29 | D6: =C6/B6 -> 1056.0418
A7: Gift Card | B7: 230 | C7: 246323.92 | D7: =C7/B7 -> 1070.9736
A8: Debit Card | B8: 232 | C8: 232361.18 | D8: =C8/B8 -> 1001.5568
A9: TOTAL | B9: =SUM(B4:B8) -> 1200 | C9: =SUM(C4:C8) -> 1264762 | D9: =AVERAGE(D4:D8) -> 1054.6694

Sheet Referral Source
A1: REFERRAL SOURCE ANALYSIS — SUM + AVG + COUNT + GROUP BY + ORDER BY
A2: SELECT ReferralSource, COUNT(*) AS Orders, ROUND(SUM(TotalPrice),2) AS Revenue, ROUND(AVG(TotalPrice),2) AS AvgOrder FROM orders GROUP BY ReferralSource ORDER BY Revenue DESC
A3: Referral Source | B3: Orders | C3: Revenue | D3: Avg Order | E3: % Revenue
A4: Instagram | B4: 259 | C4: 275285.45 | D4: 1062.88 | E4: =C4/SUM($C$4:$C$8) -> 0.21765791
A5: Email | B5: 250 | C5: 261808.55 | D5: 1047.23 | E5: =C5/SUM($C$4:$C$8) -> 0.20700223
A6: Google | B6: 241 | C6: 250441.48 | D6: 1039.18 | E6: =C6/SUM($C$4:$C$8) -> 0.19801472
A7: Facebook | B7: 228 | C7: 250410.9 | D7: 1098.29 | E7: =C7/SUM($C$4:$C$8) -> 0.19799054
A8: Referral | B8: 222 | C8: 226815.58 | D8: 1021.69 | E8: =C8/SUM($C$4:$C$8) -> 0.1793346
A9: TOTAL | B9: =SUM(B4:B8) -> 1200 | C9: =SUM(C4:C8) -> 1264762 | D9: =AVERAGE(D4:D8) -> 1053.854 | E9: =SUM(E4:E8) -> 1

Sheet Coupon Impact
A1: COUPON CODE IMPACT — CASE WHEN + SUM + AVG + GROUP BY
A2: SELECT CASE WHEN CouponCode IS NULL THEN 'No Coupon' ELSE CouponCode END AS Coupon, COUNT(*) AS Orders, ROUND(AVG(TotalPrice),2) AS AvgRevenue, ROUND(SUM(TotalPrice),2) AS TotalRevenue FROM orders GROUP BY Coupon ORDER BY TotalRevenue DESC
A3: Coupon | B3: Orders | C3: Avg Revenue | D3: Total Revenue | E3: % of Total
A4: FREESHIP | B4: 313 | C4: 1070.41 | D4: 335036.99 | E4: =D4/SUM($D$4:$D$7) -> 0.26490122
A5: No Coupon | B5: 309 | C5: 1043.37 | D5: 322401.41 | E5: =D5/SUM($D$4:$D$7) -> 0.25491074
A6: SAVE10 | B6: 286 | C6: 1065.87 | D6: 304840.02 | E6: =D6/SUM($D$4:$D$7) -> 0.24102561
A7: WINTER15 | B7: 292 | C7: 1035.9 | D7: 302483.54 | E7: =D7/SUM($D$4:$D$7) -> 0.23916243
A8: TOTAL | B8: =SUM(B4:B7) -> 1200 | C8: =AVERAGE(C4:C7) -> 1053.8875 | D8: =SUM(D4:D7) -> 1264762 | E8: =SUM(E4:E7) -> 1

Sheet Top 10 Orders
A1: TOP 10 ORDERS BY VALUE — ORDER BY + LIMIT
A2: SELECT OrderID, Product, CustomerID, TotalPrice, OrderStatus FROM orders ORDER BY TotalPrice DESC LIMIT 10
A3: Order ID | B3: Product | C3: Customer ID | D3: Total Price | E3: Status
A4: ORD200789 | B4: Tablet | C4: C57276 | D4: 3456.4 | E4: Delivered
A5: ORD201122 | B5: Monitor | C5: C38840 | D5: 3390.95 | E5: Returned
A6: ORD200632 | B6: Laptop | C6: C67260 | D6: 3390.8 | E6: Delivered
A7: ORD200469 | B7: Chair | C7: C13877 | D7: 3384.9 | E7: Cancelled
A8: ORD200328 | B8: Tablet | C8: C18404 | D8: 3370.2 | E8: Cancelled
A9: ORD200107 | B9: Printer | C9: C16775 | D9: 3353.75 | E9: Shipped
A10: ORD200326 | B10: Laptop | C10: C65986 | D10: 3352.4 | E10: Returned
A11: ORD201065 | B11: Printer | C11: C47778 | D11: 3334 | E11: Delivered
A12: ORD201031 | B12: Phone | C12: C59183 | D12: 3322.55 | E12: Pending
A13: ORD200463 | B13: Laptop | C13: C25276 | D13: 3313.9 | E13: Shipped

Sheet Monthly Trend
A1: MONTHLY REVENUE TREND — strftime + GROUP BY + ORDER BY
A2: SELECT strftime('%Y-%m', Date) AS Month, COUNT(*) AS Orders, ROUND(SUM(TotalPrice),2) AS Revenue FROM orders GROUP BY Month ORDER BY Month
A3: Month | B3: Orders | C3: Revenue | D3: MoM Change
A4: 2023-01 | B4: 47 | C4: 56685.75 | D4: —
A5: 2023-02 | B5: 37 | C5: 40117.66 | D5: =(C5-C4)/C4 -> -0.29227963
A6: 2023-03 | B6: 43 | C6: 48609.37 | D6: =(C6-C5)/C5 -> 0.21167012
A7: 2023-04 | B7: 31 | C7: 27751.71 | D7: =(C7-C6)/C6 -> -0.42908723
A8: 2023-05 | B8: 49 | C8: 63836.84 | D8: =(C8-C7)/C7 -> 1.3002849
A9: 2023-06 | B9: 45 | C9: 49500.19 | D9: =(C9-C8)/C8 -> -0.2245827
A10: 2023-07 | B10: 44 | C10: 42820.66 | D10: =(C10-C9)/C9 -> -0.13493948
A11: 2023-08 | B11: 51 | C11: 54352.14 | D11: =(C11-C10)/C10 -> 0.26929711
A12: 2023-09 | B12: 29 | C12: 29526.67 | D12: =(C12-C11)/C11 -> -0.45675239
A13: 2023-10 | B13: 47 | C13: 52607.85 | D13: =(C13-C12)/C12 -> 0.78170617
A14: 2023-11 | B14: 41 | C14: 43079.67 | D14: =(C14-C13)/C13 -> -0.18111708
A15: 2023-12 | B15: 46 | C15: 43754.73 | D15: =(C15-C14)/C14 -> 0.015670036
A16: 2024-01 | B16: 32 | C16: 38528.08 | D16: =(C16-C15)/C15 -> -0.11945337
... A33: 2025-06 | B33: 49 | C33: 53047.4 | D33: =(C33-C32)/C32 -> 0.22238496
A34: TOTAL | B34: =SUM(B4:B33) -> 1200 | C34: =SUM(C4:C33) -> 1264762 | D34: =AVERAGE(D5:D33) -> 0.074045456
